README.rst
setup.py
pylivereloader/__init__.py
pylivereloader/core.py
pylivereloader.egg-info/PKG-INFO
pylivereloader.egg-info/SOURCES.txt
pylivereloader.egg-info/dependency_links.txt
pylivereloader.egg-info/top_level.txt