Metadata-Version: 1.1
Name: pylivereloader
Version: 1.2
Summary: Script live reloader for production environment
Home-page: http://github.com/Z3R0xLEGEND/pylivereloader
Author: Z3R0xLEGEND
Author-email: legend.z3r00.pro@gmail.com
License: MIT
Platform: ALL
Classifier: Programming Language :: Python :: 3.9
Classifier: Development Status :: 5 - Production/Stable
Classifier: Natural Language :: English
Classifier: Operating System :: OS Independent
Classifier: Topic :: Software Development :: Testing
